[
  {
    "id": "ASMPV_016",
    "la": 45.3108,
    "lo": 9.01861
  },
  {
    "id": "BLG02",
    "la": 45.16109,
    "lo": 9.3027
  },
  {
    "id": "BLG03",
    "la": 45.16079,
    "lo": 9.30274
  },
  {
    "id": "BLG04",
    "la": 45.15712,
    "lo": 9.30901
  },
  {
    "id": "BLG05",
    "la": 45.16917,
    "lo": 9.31579
  },
  {
    "id": "BLG06",
    "la": 45.15582,
    "lo": 9.3205
  },
  {
    "id": "BRN06",
    "la": 45.07444,
    "lo": 9.27406
  },
  {
    "id": "BRN07",
    "la": 45.05904,
    "lo": 9.24747
  },
  {
    "id": "BRN08_1",
    "la": 45.05016,
    "lo": 9.25502
  },
  {
    "id": "BRN08_2",
    "la": 45.05019,
    "lo": 9.25502
  },
  {
    "id": "BRN09",
    "la": 45.08352,
    "lo": 9.26464
  },
  {
    "id": "CL002_1",
    "la": 45.31068,
    "lo": 8.74752
  },
  {
    "id": "CL003_1",
    "la": 45.31141,
    "lo": 8.74227
  },
  {
    "id": "CL004_1",
    "la": 45.29922,
    "lo": 8.74545
  },
  {
    "id": "CL005_1",
    "la": 45.31386,
    "lo": 8.74704
  },
  {
    "id": "CL006_1",
    "la": 45.31003,
    "lo": 8.74918
  },
  {
    "id": "CPV01",
    "la": 45.2492,
    "lo": 9.12985
  },
  {
    "id": "CPV02",
    "la": 45.2548,
    "lo": 9.1245
  },
  {
    "id": "CPV02_2",
    "la": 45.2494,
    "lo": 9.130049999999999
  },
  {
    "id": "CPV03",
    "la": 45.25674,
    "lo": 9.14187
  },
  {
    "id": "CPV04",
    "la": 45.22947,
    "lo": 9.12457
  },
  {
    "id": "CPV05",
    "la": 45.22959,
    "lo": 9.13367
  },
  {
    "id": "CPV06",
    "la": 45.25574,
    "lo": 9.14329
  },
  {
    "id": "CS002_1",
    "la": 45.3448,
    "lo": 8.82557
  },
  {
    "id": "CS050_1",
    "la": 45.35731,
    "lo": 8.81376
  },
  {
    "id": "CS051_1",
    "la": 45.36737,
    "lo": 8.81421
  },
  {
    "id": "CS052_1",
    "la": 45.36478,
    "lo": 8.81588
  },
  {
    "id": "CS053_1",
    "la": 45.36982,
    "lo": 8.81106
  },
  {
    "id": "CSP01",
    "la": 45.3096,
    "lo": 9.0133
  },
  {
    "id": "CSP02",
    "la": 45.31508,
    "lo": 9.01153
  },
  {
    "id": "CSP03",
    "la": 45.31263,
    "lo": 9.01556
  },
  {
    "id": "CSP04",
    "la": 45.31065,
    "lo": 9.02108
  },
  {
    "id": "CT003_1",
    "la": 45.01519,
    "lo": 9.1136
  },
  {
    "id": "CT004_1",
    "la": 45.01467,
    "lo": 9.11607
  },
  {
    "id": "CT005_1",
    "la": 45.01792,
    "lo": 9.12798
  },
  {
    "id": "CT008_1",
    "la": 45.00905,
    "lo": 9.12194
  },
  {
    "id": "CT010_1",
    "la": 45.01002,
    "lo": 9.11879
  },
  {
    "id": "CT013_1",
    "la": 45.00355,
    "lo": 9.12976
  },
  {
    "id": "CT014_1",
    "la": 45.01427,
    "lo": 9.10955
  },
  {
    "id": "CT015_1",
    "la": 45.02068,
    "lo": 9.13608
  },
  {
    "id": "CT017_1",
    "la": 45.00918,
    "lo": 9.11224
  },
  {
    "id": "CVM01",
    "la": 45.13938,
    "lo": 9.1126
  },
  {
    "id": "CVM02",
    "la": 45.13829,
    "lo": 9.11944
  },
  {
    "id": "CVM03",
    "la": 45.12113,
    "lo": 9.12019
  },
  {
    "id": "GM004_1",
    "la": 45.26745,
    "lo": 8.85822
  },
  {
    "id": "GM005_1",
    "la": 45.26778,
    "lo": 8.8547
  },
  {
    "id": "GM006_1",
    "la": 45.26758,
    "lo": 8.85243
  },
  {
    "id": "GM008_1",
    "la": 45.25816,
    "lo": 8.8691
  },
  {
    "id": "GM009_1",
    "la": 45.25933,
    "lo": 8.8558
  },
  {
    "id": "GM010_1",
    "la": 45.26375,
    "lo": 8.85485
  },
  {
    "id": "GM011_1",
    "la": 45.26558,
    "lo": 8.85312
  },
  {
    "id": "GM012_1",
    "la": 45.25152,
    "lo": 8.8022
  },
  {
    "id": "GM013_1",
    "la": 45.28156,
    "lo": 8.85403
  },
  {
    "id": "GR004_1",
    "la": 45.209,
    "lo": 8.93245
  },
  {
    "id": "GR005_1",
    "la": 45.19969,
    "lo": 8.93855
  },
  {
    "id": "GR006_1",
    "la": 45.20299,
    "lo": 8.9165
  },
  {
    "id": "GR008_1",
    "la": 45.19725,
    "lo": 8.93028
  },
  {
    "id": "GR009_1",
    "la": 45.19976,
    "lo": 8.92426
  },
  {
    "id": "GR010_1",
    "la": 45.19151,
    "lo": 8.91356
  },
  {
    "id": "GR011_1",
    "la": 45.20411,
    "lo": 8.95427
  },
  {
    "id": "GR012_1",
    "la": 45.20312,
    "lo": 8.92222
  },
  {
    "id": "GR013_1",
    "la": 45.18894,
    "lo": 8.92484
  },
  {
    "id": "GSG01",
    "la": 45.25159,
    "lo": 9.16309
  },
  {
    "id": "GSG02",
    "la": 45.25151,
    "lo": 9.16297
  },
  {
    "id": "GSG04",
    "la": 45.25636,
    "lo": 9.16123
  },
  {
    "id": "GSG05",
    "la": 45.27724,
    "lo": 9.1404
  },
  {
    "id": "GSG06",
    "la": 45.28749,
    "lo": 9.14237
  },
  {
    "id": "GSG07",
    "la": 45.2914,
    "lo": 9.16474
  },
  {
    "id": "LD005_1",
    "la": 45.3091,
    "lo": 9.25769
  },
  {
    "id": "LD006_1",
    "la": 45.30542,
    "lo": 9.26549
  },
  {
    "id": "LD007_1",
    "la": 45.30698,
    "lo": 9.2703
  },
  {
    "id": "LD008_1",
    "la": 45.31504,
    "lo": 9.26924
  },
  {
    "id": "LD009_1",
    "la": 45.31716,
    "lo": 9.29618
  },
  {
    "id": "MD001_1",
    "la": 45.10138,
    "lo": 8.74495
  },
  {
    "id": "MD002_1",
    "la": 45.10282,
    "lo": 8.73937
  },
  {
    "id": "MD003_1",
    "la": 45.09368,
    "lo": 8.74681
  },
  {
    "id": "MD004_1",
    "la": 45.09306,
    "lo": 8.73933
  },
  {
    "id": "MD005_1",
    "la": 45.09007,
    "lo": 8.72866
  },
  {
    "id": "MD006_1",
    "la": 45.10102,
    "lo": 8.72649
  },
  {
    "id": "MD007_1",
    "la": 45.12339,
    "lo": 8.74261
  },
  {
    "id": "MR004_1",
    "la": 45.25605,
    "lo": 8.7257
  },
  {
    "id": "MR006_1",
    "la": 45.25727,
    "lo": 8.73324
  },
  {
    "id": "MR006_2",
    "la": 45.25747,
    "lo": 8.73344
  },
  {
    "id": "MR007_1",
    "la": 45.24739,
    "lo": 8.74944
  },
  {
    "id": "MR008_1",
    "la": 45.25628,
    "lo": 8.74246
  },
  {
    "id": "MR009_1",
    "la": 45.25631,
    "lo": 8.74279
  },
  {
    "id": "MR010_1",
    "la": 45.2571,
    "lo": 8.7476
  },
  {
    "id": "MR011_1",
    "la": 45.248,
    "lo": 8.72281
  },
  {
    "id": "MR012_1",
    "la": 45.25048,
    "lo": 8.75258
  },
  {
    "id": "MR015_1",
    "la": 45.25389,
    "lo": 8.79145
  },
  {
    "id": "RB002_1",
    "la": 45.29128,
    "lo": 8.58523
  },
  {
    "id": "RB004_1",
    "la": 45.28698,
    "lo": 8.58813
  },
  {
    "id": "RB005_1",
    "la": 45.29321,
    "lo": 8.59945
  },
  {
    "id": "RB006_1",
    "la": 45.29177,
    "lo": 8.59696
  },
  {
    "id": "RB008_1",
    "la": 45.28802,
    "lo": 8.59603
  },
  {
    "id": "RB009_1",
    "la": 45.28702,
    "lo": 8.59574
  },
  {
    "id": "RB010_1",
    "la": 45.28896,
    "lo": 8.59631
  },
  {
    "id": "RB011_1",
    "la": 45.28966,
    "lo": 8.58447
  },
  {
    "id": "RT004_1",
    "la": 44.9272,
    "lo": 9.01429
  },
  {
    "id": "RT012_1",
    "la": 44.93944,
    "lo": 8.98031
  },
  {
    "id": "RT014_1",
    "la": 44.91709,
    "lo": 9.02292
  },
  {
    "id": "SB001_1",
    "la": 45.09768,
    "lo": 8.90699
  },
  {
    "id": "SB003_1",
    "la": 45.10779,
    "lo": 8.91617
  },
  {
    "id": "SB004_1",
    "la": 45.10831,
    "lo": 8.92541
  },
  {
    "id": "SB005_1",
    "la": 45.11075,
    "lo": 8.91653
  },
  {
    "id": "SMS01",
    "la": 45.14412,
    "lo": 9.11721
  },
  {
    "id": "SMS02",
    "la": 45.14896,
    "lo": 9.12175
  },
  {
    "id": "SMS03",
    "la": 45.1654,
    "lo": 9.14017
  },
  {
    "id": "SMS04",
    "la": 45.15535,
    "lo": 9.13318
  },
  {
    "id": "SMS05",
    "la": 45.15535,
    "lo": 9.13318
  },
  {
    "id": "STR01",
    "la": 45.06474,
    "lo": 9.30034
  },
  {
    "id": "STR04",
    "la": 45.07043,
    "lo": 9.31531
  },
  {
    "id": "STR06",
    "la": 45.07282,
    "lo": 9.32063
  },
  {
    "id": "STR07",
    "la": 45.05356,
    "lo": 9.3006
  },
  {
    "id": "STR08",
    "la": 45.07942,
    "lo": 9.29622
  },
  {
    "id": "STR09",
    "la": 45.08136,
    "lo": 9.30376
  },
  {
    "id": "STR10",
    "la": 45.05796,
    "lo": 9.32219
  },
  {
    "id": "STR11",
    "la": 45.09246,
    "lo": 9.28161
  },
  {
    "id": "STR12",
    "la": 45.09114,
    "lo": 9.29542
  },
  {
    "id": "STR13",
    "la": 45.09461,
    "lo": 9.2798
  },
  {
    "id": "STR15",
    "la": 45.07513,
    "lo": 9.30708
  },
  {
    "id": "STR18",
    "la": 45.09453,
    "lo": 9.30905
  },
  {
    "id": "STR19",
    "la": 45.08326,
    "lo": 9.26443
  },
  {
    "id": "SZ004_1",
    "la": 45.32462,
    "lo": 9.2037
  },
  {
    "id": "SZ005_1",
    "la": 45.31498,
    "lo": 9.20637
  },
  {
    "id": "SZ006_1",
    "la": 45.3116,
    "lo": 9.20799
  },
  {
    "id": "VDG01",
    "la": 45.29261,
    "lo": 9.23421
  },
  {
    "id": "VDG02",
    "la": 45.29244,
    "lo": 9.23656
  },
  {
    "id": "VDG03",
    "la": 45.29312,
    "lo": 9.23908
  },
  {
    "id": "VDG04",
    "la": 45.2896,
    "lo": 9.23283
  },
  {
    "id": "VH001_1",
    "la": 44.98953,
    "lo": 8.98175
  },
  {
    "id": "VH002_1",
    "la": 44.99447,
    "lo": 8.9908
  },
  {
    "id": "VH003_1",
    "la": 44.9969,
    "lo": 9.00511
  },
  {
    "id": "VH004_1",
    "la": 44.99767,
    "lo": 9.01705
  },
  {
    "id": "VH005_1",
    "la": 44.99674,
    "lo": 9.02819
  },
  {
    "id": "VH006_1",
    "la": 44.98988,
    "lo": 9.0187
  },
  {
    "id": "VH008_1",
    "la": 44.97844,
    "lo": 9.00244
  },
  {
    "id": "VH009_1",
    "la": 44.98007,
    "lo": 8.99147
  },
  {
    "id": "VH010_1",
    "la": 45.05026,
    "lo": 9.019
  },
  {
    "id": "VH011_1",
    "la": 45.00203,
    "lo": 9.00529
  },
  {
    "id": "VH012_1",
    "la": 45.00205,
    "lo": 9.00616
  },
  {
    "id": "VH013_1",
    "la": 45.03032,
    "lo": 9.00676
  }
]